snappyx/__init__.py
snappyx/_snappyx.cpp
snappyx/_snappyx.pxd
snappyx/_snappyx.pyx
snappyx/_snappyx.so
snappyx-0.5.1.dist-info/DESCRIPTION.rst
snappyx-0.5.1.dist-info/METADATA
snappyx-0.5.1.dist-info/RECORD
snappyx-0.5.1.dist-info/WHEEL
snappyx-0.5.1.dist-info/metadata.json
snappyx-0.5.1.dist-info/top_level.txt
