Metadata-Version: 2.0
Name: snappyx
Version: 0.5.1
Summary: A simple Cython wrapper for the snappy compression library
Home-page: https://github.com/stephane-martin/snappyx
Author: Stephane Martin
Author-email: stephane.martin_github@vesperal.eu
License: see LICENSE file
Keywords: python snappy compression
Platform: UNKNOWN
Classifier: Development Status :: 4 - Beta
Classifier: Programming Language :: C++
Classifier: Programming Language :: Python :: 2.7
Classifier: Programming Language :: Python :: 3
Classifier: Programming Language :: Cython
Classifier: Operating System :: POSIX
Classifier: Topic :: Software Development :: Libraries
Classifier: Topic :: System :: Archiving :: Compression
